python_openet/__init__.py
python_openet/client.py
python_openet-0.1.0.dist-info/WHEEL
python_openet-0.1.0.dist-info/METADATA
python_openet-0.1.0.dist-info/RECORD
